skillet/__init__.py
skillet/py.typed
skillet-0.0.2.dist-info/LICENSE
skillet-0.0.2.dist-info/METADATA
skillet-0.0.2.dist-info/WHEEL
skillet-0.0.2.dist-info/top_level.txt
skillet-0.0.2.dist-info/RECORD
